napari_mrcfile_handler/__init__.py
napari_mrcfile_handler/_dock_widget.py
napari_mrcfile_handler/_reader.py
napari_mrcfile_handler/_writer.py
napari_mrcfile_handler/_tests/__init__.py
napari_mrcfile_handler/_tests/test_dock_widget.py
napari_mrcfile_handler/_tests/test_reader.py
napari_mrcfile_handler/_tests/test_writer.py
napari_mrcfile_handler-0.0.6.dist-info/LICENSE
napari_mrcfile_handler-0.0.6.dist-info/METADATA
napari_mrcfile_handler-0.0.6.dist-info/WHEEL
napari_mrcfile_handler-0.0.6.dist-info/entry_points.txt
napari_mrcfile_handler-0.0.6.dist-info/top_level.txt
napari_mrcfile_handler-0.0.6.dist-info/RECORD
