Metadata-Version: 2.1
Name: napari-mrcfile-handler
Version: 0.0.6
Summary: A simple plugin to read, write and adjust mrcfiles in napari.
Home-page: https://github.com/Croxa/napari-mrcfile_handler
Author: Philipp Schoennenbeck
Author-email: p.schoennenbeck@fz-juelich.de
License: BSD-3-Clause
Project-URL: Bug Tracker, https://github.com/Croxa/napari-mrcfile_handler/issues
Project-URL: Documentation, https://github.com/Croxa/napari-mrcfile_handler#README.md
Project-URL: Source Code, https://github.com/Croxa/napari-mrcfile_handler
Project-URL: User Support, https://github.com/Croxa/napari-mrcfile_handler/issues
Platform: UNKNOWN
Classifier: Development Status :: 2 - Pre-Alpha
Classifier: Intended Audience :: Developers
Classifier: Framework :: napari
Classifier: Topic :: Software Development :: Testing
Classifier: Programming Language :: Python
Classifier: Programming Language :: Python :: 3
Classifier: Programming Language :: Python :: 3.7
Classifier: Programming Language :: Python :: 3.8
Classifier: Programming Language :: Python :: 3.9
Classifier: Operating System :: OS Independent
Classifier: License :: OSI Approved :: BSD License
Requires-Python: >=3.7
Requires-Dist: napari-plugin-engine (>=0.1.4)
Requires-Dist: numpy
Requires-Dist: mrcfile
